extensible/__init__.py
extensible/defs.py
extensible/extensible.py
extensible/train_manager.py
extensible/extensions/__init__.py
extensible/extensions/checkpoints.py
extensible/extensions/default.py
extensible/extensions/extension.py
extensible/extensions/gradient_visualizer.py
extensible/extensions/soleil.py
extensible/extensions/utils.py
extensible-0.1.0.dist-info/METADATA
extensible-0.1.0.dist-info/WHEEL
extensible-0.1.0.dist-info/top_level.txt
extensible-0.1.0.dist-info/RECORD
