Metadata-Version: 2.1
Name: extensible
Version: 0.1.0
Summary: Context managed hooks
Home-page: https://github.com/zepedaj/extensible
Author: Joaquin Zepeda
Requires-Dist: jztools
Requires-Dist: ploteries
Requires-Dist: soleil
